dnscontroller/__init__.py
dnscontroller/main.py
dnscontroller-0.7.dist-info/METADATA
dnscontroller-0.7.dist-info/WHEEL
dnscontroller-0.7.dist-info/entry_points.txt
dnscontroller-0.7.dist-info/RECORD
