Metadata-Version: 2.4
Name: dnscontroller
Version: 0.7
Summary: A CLI tool for managing Cloudflare DNS records
Project-URL: Homepage, https://github.com/personalcomputer/dnscontroller
Author-email: John Miller <john@johngm.com>
Requires-Python: >=3.11
Requires-Dist: click>=8.1.7
Requires-Dist: cloudflare>=2.12.0
Requires-Dist: pyyaml>=6.0.1
Requires-Dist: rich-click>=1.8.8
Requires-Dist: rich>=13.7.0
